{"credits":"diamondworld.pro | vk.com/Foghost","textures":{"0":"prisonevo/bosses/extinct/texture","particle":"prisonevo/bosses/extinct/texture"},"texture_size":[128,128],"elements":[{"name":"bone3","from":[0,5,-6],"to":[16,19,22],"faces":{"north":{"uv":[0,8,2,9.75],"texture":"#0"},"east":{"uv":[5.5,8,2,9.75],"texture":"#0"},"south":{"uv":[5.5,8,7.5,9.75],"texture":"#0"},"west":{"uv":[2,8,5.5,9.75],"texture":"#0"},"up":{"uv":[2,8,0,4.5],"texture":"#0"},"down":{"uv":[4,4.5,2,8],"texture":"#0"}}},{"name":"bone4","from":[0,0,22],"to":[16,5,22],"faces":{"north":{"uv":[7.5,9.75,5.5,10.375],"texture":"#0"},"east":{"uv":[5.5,8,2,9.75],"texture":"#0"},"south":{"uv":[5.5,9.75,7.5,10.375],"texture":"#0"},"west":{"uv":[2,8,5.5,9.75],"texture":"#0"},"up":{"uv":[2,8,0,4.5],"texture":"#0"},"down":{"uv":[4,4.5,2,8],"texture":"#0"}}},{"name":"bone3","from":[0,0,-6],"to":[0,5,22],"faces":{"north":{"uv":[3.625,3.625,3.625,4.25],"texture":"#0"},"east":{"uv":[5.5,9.75,2,10.375],"texture":"#0"},"south":{"uv":[7.125,3.625,7.125,4.25],"texture":"#0"},"west":{"uv":[2,9.75,5.5,10.375],"texture":"#0"},"up":{"uv":[3.625,3.625,3.625,0.125],"texture":"#0"},"down":{"uv":[3.625,0.125,3.625,3.625],"texture":"#0"}}},{"name":"bone3","from":[16,0,-6],"to":[16,5,22],"faces":{"north":{"uv":[3.625,3.625,3.625,4.25],"texture":"#0"},"east":{"uv":[5.5,9.75,2,10.375],"texture":"#0"},"south":{"uv":[7.125,3.625,7.125,4.25],"texture":"#0"},"west":{"uv":[2,9.75,5.5,10.375],"texture":"#0"},"up":{"uv":[3.625,3.625,3.625,0.125],"texture":"#0"},"down":{"uv":[3.625,0.125,3.625,3.625],"texture":"#0"}}}],"display":{"head":{"translation":[0,-1.5,0],"scale":[1.6,1.6,1.6]}},"groups":[{"name":"bone3","origin":[0,0,-0.5],"rotation":[5,0,0],"color":0,"children":[0,1,2,3]}]}