{"textures":{"2":"modelengine:entity/kriger_damaged"},"elements":[{"from":[5.0,4.9661307,4.1976132],"to":[11.0,7.9661307,9.197613],"faces":{"east":{"uv":[10.125,3.625,9.5,4.0],"tintindex":0,"rotation":0,"texture":"#2"},"south":{"uv":[9.5,8.375,8.75,8.75],"tintindex":0,"rotation":0,"texture":"#2"},"north":{"uv":[9.5,8.0,8.75,8.375],"tintindex":0,"rotation":0,"texture":"#2"},"west":{"uv":[10.0,8.75,9.375,9.125],"tintindex":0,"rotation":0,"texture":"#2"},"up":{"uv":[6.375,8.625,7.125,8.0],"tintindex":0,"rotation":0,"texture":"#2"},"down":{"uv":[8.0,7.5,8.75,8.125],"tintindex":0,"rotation":0,"texture":"#2"}},"rotation":{"origin":[7.75,19.716131,8.447613],"angle":0.0,"axis":"x"}},{"from":[4.9,6.5948105,0.69761324],"to":[11.1,9.5948105,3.6976132],"faces":{"east":{"uv":[10.125,4.375,9.75,4.75],"tintindex":0,"rotation":0,"texture":"#2"},"south":{"uv":[9.625,2.625,8.875,3.0],"tintindex":0,"rotation":0,"texture":"#2"},"north":{"uv":[9.375,8.75,8.625,9.125],"tintindex":0,"rotation":0,"texture":"#2"},"west":{"uv":[3.125,9.75,2.75,10.125],"tintindex":0,"rotation":0,"texture":"#2"},"up":{"uv":[8.875,3.375,9.625,3.0],"tintindex":0,"rotation":0,"texture":"#2"},"down":{"uv":[8.875,6.0,9.625,6.375],"tintindex":0,"rotation":0,"texture":"#2"}},"rotation":{"origin":[8.5,7.0948105,2.1976132],"angle":-45.0,"axis":"x"}},{"from":[5.0,6.0,2.0],"to":[11.0,9.0,5.0],"faces":{"east":{"uv":[5.375,9.75,5.0,10.125],"tintindex":0,"rotation":0,"texture":"#2"},"south":{"uv":[9.75,4.375,9.0,4.75],"tintindex":0,"rotation":0,"texture":"#2"},"north":{"uv":[9.75,2.0,9.0,2.375],"tintindex":0,"rotation":0,"texture":"#2"},"west":{"uv":[10.125,4.75,9.75,5.125],"tintindex":0,"rotation":0,"texture":"#2"},"up":{"uv":[9.0,5.125,9.75,4.75],"tintindex":0,"rotation":0,"texture":"#2"},"down":{"uv":[9.125,0.5,9.875,0.875],"tintindex":0,"rotation":0,"texture":"#2"}},"rotation":{"origin":[8.5,7.5,2.0],"angle":22.5,"axis":"x"}}]}