{"textures":{"0":"modelengine:entity/kriger"},"elements":[{"from":[8.0,6.5,4.0],"to":[18.0,9.5,8.0],"faces":{"east":{"uv":[13.1125,7.0125,12.5125,7.4875],"tintindex":0,"rotation":0,"texture":"#0"},"south":{"uv":[5.9875,11.3875,4.7625,11.8625],"tintindex":0,"rotation":0,"texture":"#0"},"north":{"uv":[12.4875,7.0125,11.2625,7.3625],"tintindex":0,"rotation":0,"texture":"#0"},"west":{"uv":[0.6125,9.5125,0.0125,9.9875],"tintindex":0,"rotation":0,"texture":"#0"},"up":{"uv":[10.3875,6.9875,11.6125,6.3875],"tintindex":0,"rotation":0,"texture":"#0"},"down":{"uv":[10.3875,9.3875,11.6125,9.9875],"tintindex":0,"rotation":0,"texture":"#0"}}},{"from":[18.0,5.5,2.0],"to":[22.0,11.5,9.0],"faces":{"east":{"uv":[3.1125,11.1375,2.2625,11.8625],"tintindex":0,"rotation":0,"texture":"#0"},"south":{"uv":[4.9875,12.5125,4.5125,13.2375],"tintindex":0,"rotation":0,"texture":"#0"},"north":{"uv":[0.9875,12.5125,0.5125,13.2375],"tintindex":0,"rotation":0,"texture":"#0"},"west":{"uv":[9.3625,10.8875,8.5125,11.6125],"tintindex":0,"rotation":0,"texture":"#0"},"up":{"uv":[9.7625,12.9875,10.2375,12.1375],"tintindex":0,"rotation":0,"texture":"#0"},"down":{"uv":[12.1375,10.0125,12.6125,10.8625],"tintindex":0,"rotation":0,"texture":"#0"}}}]}