{"textures":{"0":"modelengine:entity/skeleton_archer"},"elements":[{"from":[6.440915,0.9392891,5.25036],"to":[9.440914,7.939289,8.2503605],"faces":{"east":{"uv":[4.875,8.125,5.25,9.0],"tintindex":0,"rotation":0,"texture":"#0"},"south":{"uv":[5.375,8.125,5.75,9.0],"tintindex":0,"rotation":0,"texture":"#0"},"north":{"uv":[4.375,8.125,4.75,9.0],"tintindex":0,"rotation":0,"texture":"#0"},"west":{"uv":[5.875,8.125,6.25,9.0],"tintindex":0,"rotation":0,"texture":"#0"},"up":{"uv":[7.75,11.0,7.375,10.625],"tintindex":0,"rotation":0,"texture":"#0"},"down":{"uv":[8.875,10.625,8.5,11.0],"tintindex":0,"rotation":0,"texture":"#0"}},"rotation":{"origin":[7.974518,4.371584,8.248454],"angle":22.5,"axis":"x"}},{"from":[5.940915,1.9392891,4.75036],"to":[9.940914,6.939289,8.7503605],"faces":{"east":{"uv":[6.375,8.125,6.875,8.75],"tintindex":0,"rotation":0,"texture":"#0"},"south":{"uv":[8.25,4.25,8.75,4.875],"tintindex":0,"rotation":0,"texture":"#0"},"north":{"uv":[3.125,4.25,3.625,4.875],"tintindex":0,"rotation":0,"texture":"#0"},"west":{"uv":[8.375,1.375,8.875,2.0],"tintindex":0,"rotation":0,"texture":"#0"},"up":{"uv":[9.75,0.5,9.25,0.0],"tintindex":0,"rotation":0,"texture":"#0"},"down":{"uv":[10.0,0.625,9.5,1.125],"tintindex":0,"rotation":0,"texture":"#0"}},"rotation":{"origin":[7.974518,4.371584,8.248454],"angle":22.5,"axis":"x"}}]}