{"textures":{"0":"modelengine:entity/wolf_big"},"elements":[{"from":[4.0,7.5,7.25],"to":[11.999999,15.5,14.25],"faces":{"east":{"uv":[12.25,4.125,13.125,5.125],"tintindex":0,"rotation":0,"texture":"#0"},"south":{"uv":[15.0,4.125,16.0,5.125],"tintindex":0,"rotation":0,"texture":"#0"},"north":{"uv":[13.125,4.125,14.125,5.125],"tintindex":0,"rotation":0,"texture":"#0"},"west":{"uv":[14.125,4.125,15.0,5.125],"tintindex":0,"rotation":0,"texture":"#0"},"up":{"uv":[14.125,4.125,13.125,3.25],"tintindex":0,"rotation":0,"texture":"#0"},"down":{"uv":[15.125,3.25,14.125,4.125],"tintindex":0,"rotation":0,"texture":"#0"}}},{"from":[5.5,8.5,2.25],"to":[10.5,12.5,8.25],"faces":{"east":{"uv":[13.25,2.75,14.0,3.25],"tintindex":0,"rotation":0,"texture":"#0"},"south":{"uv":[15.375,2.75,16.0,3.25],"tintindex":0,"rotation":0,"texture":"#0"},"north":{"uv":[14.0,2.75,14.625,3.25],"tintindex":0,"rotation":0,"texture":"#0"},"west":{"uv":[14.625,2.75,15.375,3.25],"tintindex":0,"rotation":0,"texture":"#0"},"up":{"uv":[14.625,2.75,14.0,2.0],"tintindex":0,"rotation":0,"texture":"#0"},"down":{"uv":[15.25,2.0,14.625,2.75],"tintindex":0,"rotation":0,"texture":"#0"}}}]}