{"textures":{"0":"modelengine:entity/santa_anim"},"elements":[{"from":[6.75,-5.0,5.25],"to":[12.75,1.0,11.25],"faces":{"east":{"uv":[12.625,3.125,11.875,3.875],"tintindex":0,"rotation":0,"texture":"#0"},"south":{"uv":[13.375,3.125,12.625,3.875],"tintindex":0,"rotation":0,"texture":"#0"},"north":{"uv":[11.875,3.125,11.125,3.875],"tintindex":0,"rotation":0,"texture":"#0"},"west":{"uv":[11.125,3.125,11.25,3.875],"tintindex":0,"rotation":0,"texture":"#0"},"up":{"uv":[11.875,3.125,11.125,3.25],"tintindex":0,"rotation":0,"texture":"#0"},"down":{"uv":[13.375,3.75,12.625,3.875],"tintindex":0,"rotation":0,"texture":"#0"}}},{"from":[7.25,-9.0,5.25],"to":[11.25,-5.0,10.25],"faces":{"east":{"uv":[12.25,3.875,11.625,4.375],"tintindex":0,"rotation":0,"texture":"#0"},"south":{"uv":[12.75,3.875,12.25,4.375],"tintindex":0,"rotation":0,"texture":"#0"},"north":{"uv":[11.625,3.875,11.125,4.375],"tintindex":0,"rotation":0,"texture":"#0"},"west":{"uv":[13.375,3.875,12.75,4.375],"tintindex":0,"rotation":0,"texture":"#0"},"down":{"uv":[12.25,4.375,11.625,4.875],"tintindex":0,"rotation":90,"texture":"#0"}}},{"from":[6.75,1.0,6.25],"to":[11.75,8.0,10.25],"faces":{"east":{"uv":[12.25,2.25,11.75,3.125],"tintindex":0,"rotation":0,"texture":"#0"},"south":{"uv":[12.875,2.25,12.25,3.125],"tintindex":0,"rotation":0,"texture":"#0"},"north":{"uv":[11.75,2.25,11.125,3.125],"tintindex":0,"rotation":0,"texture":"#0"},"west":{"uv":[12.875,2.25,12.75,3.125],"tintindex":0,"rotation":0,"texture":"#0"},"up":{"uv":[12.875,2.25,13.5,2.75],"tintindex":0,"rotation":0,"texture":"#0"}}}]}