{"textures":{"0":"modelengine:entity/frost"},"elements":[{"from":[-16.0,-5.0,1.5],"to":[8.0,8.0,14.5],"faces":{"east":{"uv":[3.125,12.5625,2.3125,13.375],"tintindex":0,"rotation":0,"texture":"#0"},"south":{"uv":[4.625,12.5625,3.125,13.375],"tintindex":0,"rotation":0,"texture":"#0"},"north":{"uv":[2.3125,12.5625,0.8125,13.375],"tintindex":0,"rotation":0,"texture":"#0"},"west":{"uv":[0.8125,12.5625,0.0,13.375],"tintindex":0,"rotation":0,"texture":"#0"},"up":{"uv":[0.8125,12.5625,2.3125,11.75],"tintindex":0,"rotation":0,"texture":"#0"},"down":{"uv":[2.3125,11.75,3.8125,12.5625],"tintindex":0,"rotation":0,"texture":"#0"}}}]}