{"textures":{"1":"modelengine:entity/darkershell"},"elements":[{"from":[2.6000004,-7.0,4.8],"to":[12.6,8.0,12.8],"faces":{"east":{"uv":[1.75,11.6875,2.25,12.625],"tintindex":0,"rotation":0,"texture":"#1"},"south":{"uv":[11.3125,8.5,11.9375,9.4375],"tintindex":0,"rotation":0,"texture":"#1"},"north":{"uv":[11.3125,7.5625,11.9375,8.5],"tintindex":0,"rotation":0,"texture":"#1"},"west":{"uv":[2.25,11.6875,2.75,12.625],"tintindex":0,"rotation":0,"texture":"#1"},"up":{"uv":[8.1875,12.375,7.5625,11.875],"tintindex":0,"rotation":0,"texture":"#1"},"down":{"uv":[4.8125,11.9375,4.1875,12.4375],"tintindex":0,"rotation":0,"texture":"#1"}}}]}