{"textures":{"0":"modelengine:entity/cursed_knight"},"elements":[{"from":[4.75,-10.0,4.5],"to":[8.75,-5.0,9.5],"faces":{"east":{"uv":[5.375,0.625,4.75,1.25],"tintindex":0,"rotation":0,"texture":"#0"},"south":{"uv":[4.75,1.25,5.25,1.875],"tintindex":0,"rotation":0,"texture":"#0"},"north":{"uv":[4.75,0.625,4.25,1.25],"tintindex":0,"rotation":0,"texture":"#0"},"west":{"uv":[4.25,1.875,4.875,2.5],"tintindex":0,"rotation":0,"texture":"#0"},"up":{"uv":[4.25,0.625,4.75,0.75],"tintindex":0,"rotation":0,"texture":"#0"},"down":{"uv":[4.25,1.25,4.75,1.875],"tintindex":0,"rotation":0,"texture":"#0"}}},{"from":[4.25,-5.0,5.5],"to":[9.25,2.0,9.5],"faces":{"east":{"uv":[7.75,0.0,7.25,0.875],"tintindex":0,"rotation":0,"texture":"#0"},"south":{"uv":[8.375,0.0,7.75,0.875],"tintindex":0,"rotation":0,"texture":"#0"},"north":{"uv":[7.75,0.0,8.375,0.875],"tintindex":0,"rotation":0,"texture":"#0"},"west":{"uv":[8.25,0.0,8.375,0.875],"tintindex":0,"rotation":0,"texture":"#0"},"up":{"uv":[7.25,1.375,7.875,0.875],"tintindex":0,"rotation":0,"texture":"#0"},"down":{"uv":[8.375,0.75,7.75,0.875],"tintindex":0,"rotation":0,"texture":"#0"}}}]}